kmz_custom_maps/__init__.py
kmz_custom_maps/run.py
kmz_custom_maps-0.1.0.dist-info/LICENSE
kmz_custom_maps-0.1.0.dist-info/METADATA
kmz_custom_maps-0.1.0.dist-info/WHEEL
kmz_custom_maps-0.1.0.dist-info/top_level.txt
kmz_custom_maps-0.1.0.dist-info/RECORD
