Metadata-Version: 2.1
Name: kmz-custom-maps
Version: 0.1.0
Summary: River forecasting package
Author-email: johannes Hendriks <johannes.n.hendriks@gmail.com>
Classifier: Programming Language :: Python :: 3
Classifier: License :: OSI Approved :: MIT License
Classifier: Operating System :: OS Independent
Requires-Python: >=3.9
License-File: LICENSE
Requires-Dist: numpy (<1.25.0,>=1.24.0)
Requires-Dist: Pillow (<9.5.0,>=9.4.0)
Requires-Dist: lxml (<4.10.0,>=4.9.0)
Requires-Dist: cssselect (<1.3.0,>=1.2.0)
